{"P16": {"labels": ["\u77ed\u6587", "\u4ee3\u7801"], "postTitle": "AutoHotkey \u81ea\u4ea7\u751f\u7a0b\u5e8f (Quine)", "postUrl": "post/AutoHotkey%20-zi-chan-sheng-cheng-xu-%20%28Quine%29.html", "createdDate": "2024-12-11", "dateLabelColor": "#bc4c00"}, "P15": {"labels": ["\u4ee3\u7801"], "postTitle": "\u4f2a\u88c5\u6210 Windows \u6279\u5904\u7406\u811a\u672c\u7684\u5404\u4e2a\u8bed\u8a00", "postUrl": "post/wei-zhuang-cheng-%20Windows%20-pi-chu-li-jiao-ben-de-ge-ge-yu-yan.html", "createdDate": "2024-12-10", "dateLabelColor": "#bc4c00"}, "P14": {"labels": ["\u77ed\u6587"], "postTitle": "\u5c06\u6587\u4ef6\u5dee\u5f02\u5bfc\u51fa\u4e3a HTML", "postUrl": "post/jiang-wen-jian-cha-yi-dao-chu-wei-%20HTML.html", "createdDate": "2024-04-13", "dateLabelColor": "#bc4c00"}, "P13": {"labels": ["\u77ed\u6587", "\u4ee3\u7801"], "postTitle": "\u4e3a eMule (community) \u7f16\u8bd1\u4e2d\u6587\u7ffb\u8bd1\u52a8\u6001\u5e93", "postUrl": "post/wei-%20eMule%20%28community%29%20-bian-yi-zhong-wen-fan-yi-dong-tai-ku.html", "createdDate": "2024-04-06", "dateLabelColor": "#bc4c00"}, "P12": {"labels": ["\u4ee3\u7801"], "postTitle": "PowerShell \u6267\u884c\u7a0b\u5e8f\u5e76\u590d\u7528\u7ec8\u7aef", "postUrl": "post/PowerShell%20-zhi-xing-cheng-xu-bing-fu-yong-zhong-duan.html", "createdDate": "2024-04-01", "dateLabelColor": "#bc4c00"}, "P7": {"labels": ["\u60f3\u6cd5"], "postTitle": "\u5173\u4e8e\u865a\u5c81\u7684\u5b9a\u4e49", "postUrl": "post/guan-yu-xu-sui-de-ding-yi.html", "createdDate": "2024-03-07", "dateLabelColor": "#bc4c00"}, "P1": {"labels": ["\u77ed\u6587"], "postTitle": "\u535a\u5ba2\u8fc1\u79fb\u5230 Github Issues", "postUrl": "post/bo-ke-qian-yi-dao-%20Github%20Issues.html", "createdDate": "2024-03-07", "dateLabelColor": "#bc4c00"}, "P8": {"labels": ["\u77ed\u6587"], "postTitle": "VSCode \u8fde\u63a5\u65e7\u7248 glibc \u8fdc\u7a0b", "postUrl": "post/VSCode%20-lian-jie-jiu-ban-%20glibc%20-yuan-cheng.html", "createdDate": "2024-02-27", "dateLabelColor": "#bc4c00"}, "P11": {"labels": ["\u8fc1\u79fb"], "postTitle": "\u9f99\u4e66\u8bfb\u4e66\u7b14\u8bb0 0x02: \u8bcd\u6cd5\u5206\u6790\u5668", "postUrl": "post/long-shu-du-shu-bi-ji-%200x02-%20-ci-fa-fen-xi-qi.html", "createdDate": "2022-04-04", "dateLabelColor": "#1f883d"}, "P6": {"labels": ["\u8fc1\u79fb"], "postTitle": "\u5728 Windows \u7ec8\u7aef\u91cc\u6307\u5b9a PowerShell \u914d\u7f6e\u6587\u4ef6", "postUrl": "post/zai-%20Windows%20-zhong-duan-li-zhi-ding-%20PowerShell%20-pei-zhi-wen-jian.html", "createdDate": "2022-03-17", "dateLabelColor": "#1f883d"}, "P10": {"labels": ["\u8fc1\u79fb"], "postTitle": "\u9f99\u4e66\u8bfb\u4e66\u7b14\u8bb0 0x01: \u4f8b\u7a0b 2-27", "postUrl": "post/long-shu-du-shu-bi-ji-%200x01-%20-li-cheng-%202-27.html", "createdDate": "2021-04-24", "dateLabelColor": "#0969da"}, "P9": {"labels": ["\u8fc1\u79fb"], "postTitle": "\u9f99\u4e66\u8bfb\u4e66\u7b14\u8bb0 0x00", "postUrl": "post/long-shu-du-shu-bi-ji-%200x00.html", "createdDate": "2021-04-13", "dateLabelColor": "#0969da"}, "P5": {"labels": ["\u8fc1\u79fb"], "postTitle": "\u4fdd\u6301 JBL go 2 \u6d3b\u8dc3", "postUrl": "post/bao-chi-%20JBL%20go%202%20-huo-yue.html", "createdDate": "2020-04-23", "dateLabelColor": "#bc4c00"}, "P3": {"labels": ["\u8fc1\u79fb"], "postTitle": "Hexo \u547d\u4ee4\u7b14\u8bb0", "postUrl": "post/Hexo%20-ming-ling-bi-ji.html", "createdDate": "2020-03-25", "dateLabelColor": "#bc4c00"}, "P4": {"labels": ["\u8fc1\u79fb"], "postTitle": "\u5728\u5bb6\u5ead\u670d\u52a1\u5668\u4e2d\u8bbe\u7f6e Home Assistant", "postUrl": "post/zai-jia-ting-fu-wu-qi-zhong-she-zhi-%20Home%20Assistant.html", "createdDate": "2019-01-04", "dateLabelColor": "#A333D0"}, "P2": {"labels": ["\u8fc1\u79fb"], "postTitle": "\u5173\u4e8e\u8fd9\u4e2a\u7ad9\u70b9", "postUrl": "post/guan-yu-zhe-ge-zhan-dian.html", "createdDate": "2017-04-30", "dateLabelColor": "#0969da"}, "labelColorDict": {"\u4ee3\u7801": "#506CAF", "\u60f3\u6cd5": "#5319e7", "\u65e5\u5e38": "#7F59A9", "\u6c49\u5b57": "#bfd4f2", "\u77ed\u6587": "#E89F6E", "\u8fc1\u79fb": "#541F0B"}}